drsai_ui/__init__.py
drsai_ui/run_ui.py
drsai_ui/agent_factory/__init__.py
drsai_ui/agent_factory/agent_mode_cofigs.py
drsai_ui/agent_factory/load_agent.py
drsai_ui/agent_factory/components/__init__.py
drsai_ui/agent_factory/components/memory/__init__.py
drsai_ui/agent_factory/components/memory/load_memory_cofig.py
drsai_ui/agent_factory/local_agents/__init__.py
drsai_ui/agent_factory/local_agents/ragflow_agent.py
drsai_ui/agent_factory/magentic_one/__init__.py
drsai_ui/agent_factory/magentic_one/_cli.py
drsai_ui/agent_factory/magentic_one/approval_guard.py
drsai_ui/agent_factory/magentic_one/check_docker.py
drsai_ui/agent_factory/magentic_one/guarded_action.py
drsai_ui/agent_factory/magentic_one/magentic_ui_config.py
drsai_ui/agent_factory/magentic_one/task_team.py
drsai_ui/agent_factory/magentic_one/agents/__init__.py
drsai_ui/agent_factory/magentic_one/agents/_coder.py
drsai_ui/agent_factory/magentic_one/agents/_user_proxy.py
drsai_ui/agent_factory/magentic_one/agents/_utils.py
drsai_ui/agent_factory/magentic_one/agents/user_proxy.py
drsai_ui/agent_factory/magentic_one/agents/drsai_agents/__init__.py
drsai_ui/agent_factory/magentic_one/agents/drsai_agents/drsai_agent.py
drsai_ui/agent_factory/magentic_one/agents/file_surfer/__init__.py
drsai_ui/agent_factory/magentic_one/agents/file_surfer/_browser_code_helpers.py
drsai_ui/agent_factory/magentic_one/agents/file_surfer/_code_markdown_file_browser.py
drsai_ui/agent_factory/magentic_one/agents/file_surfer/_file_surfer.py
drsai_ui/agent_factory/magentic_one/agents/file_surfer/_tool_definitions.py
drsai_ui/agent_factory/magentic_one/agents/users/__init__.py
drsai_ui/agent_factory/magentic_one/agents/users/_dummy_user_proxy.py
drsai_ui/agent_factory/magentic_one/agents/users/_metadata_user_proxy.py
drsai_ui/agent_factory/magentic_one/agents/web_surfer/__init__.py
drsai_ui/agent_factory/magentic_one/agents/web_surfer/_cua_web_surfer.py
drsai_ui/agent_factory/magentic_one/agents/web_surfer/_events.py
drsai_ui-0.0.9.dist-info/METADATA
drsai_ui-0.0.9.dist-info/WHEEL
drsai_ui-0.0.9.dist-info/entry_points.txt
drsai_ui-0.0.9.dist-info/RECORD
